caex2/__init__.py
caex2/extractor.py
caex2-1.0.2.dist-info/licenses/LICENSE
caex2-1.0.2.dist-info/METADATA
caex2-1.0.2.dist-info/WHEEL
caex2-1.0.2.dist-info/entry_points.txt
caex2-1.0.2.dist-info/top_level.txt
caex2-1.0.2.dist-info/RECORD
