Metadata-Version: 2.4
Name: caex2
Version: 1.0.2
Summary: Automatically extract all exercises from a carpentries lesson.
Author: Sven van der Burg, Dafne van Kuppevelt
Author-email: Djura Smits <d.smits@esciencecenter.nl>
Project-URL: Homepage, https://github.com/esciencecenter-digital-skills/carpentries-exercises-extractor
Keywords: Extract,Exercises
Classifier: Development Status :: 2 - Pre-Alpha
Classifier: Natural Language :: English
Classifier: Intended Audience :: Education
Classifier: Programming Language :: Python :: 3
Classifier: Programming Language :: Python :: 3.8
Classifier: Programming Language :: Python :: 3.9
Requires-Python: >=3.8
License-File: LICENSE
Requires-Dist: click>=8.1.8
Requires-Dist: gitpython>=3.1.46
Provides-Extra: publishing
Requires-Dist: twine; extra == "publishing"
Requires-Dist: wheel; extra == "publishing"
Dynamic: license-file
